moderngov/__init__.py
moderngov/api.py
moderngov/mgq.py
moderngov-0.3.0.dist-info/entry_points.txt
moderngov-0.3.0.dist-info/LICENSE
moderngov-0.3.0.dist-info/WHEEL
moderngov-0.3.0.dist-info/METADATA
moderngov-0.3.0.dist-info/RECORD
