Metadata-Version: 2.1
Name: moderngov
Version: 0.3.0
Summary: 
Home-page: https://github.com/afdy/moderngov
License: GPL-3.0
Author: Adam Ford
Author-email: feel.wires_0c@icloud.com
Requires-Python: >=3.10,<4.0
Classifier: License :: OSI Approved :: GNU General Public License v3 (GPLv3)
Classifier: Programming Language :: Python :: 3
Classifier: Programming Language :: Python :: 3.10
Classifier: Programming Language :: Python :: 3.11
Requires-Dist: diskcache (>=5.4.0,<6.0.0)
Requires-Dist: requests (>=2.28.1,<3.0.0)
Requires-Dist: validators (>=0.20.0,<0.21.0)
Requires-Dist: xmltodict (>=0.13.0,<0.14.0)
